ssb_libtest75/__init__.py
ssb_libtest75/__main__.py
ssb_libtest75/functions.py
ssb_libtest75/py.typed
ssb_libtest75-0.0.2.dist-info/LICENSE
ssb_libtest75-0.0.2.dist-info/METADATA
ssb_libtest75-0.0.2.dist-info/WHEEL
ssb_libtest75-0.0.2.dist-info/entry_points.txt
ssb_libtest75-0.0.2.dist-info/RECORD
